irregular-chars/__init__.py
irregular-chars/zero_width.py
irregular_chars/__init__.py
irregular_chars/ivs.py
irregular_chars/sound_symbol.py
irregular_chars/space.py
irregular_chars/splitted.py
irregular_chars/unicodes.py
irregular_chars/utils.py
irregular_chars/width.py
irregular_chars/zero_width.py
tests/__init__.py
tests/test_ivs.py
tests/test_sound_symbols.py
tests/test_unicodes.py
tests/test_width.py
tests/test_zero_width_spaces.py
irregular_chars-1.4.0.dist-info/LICENSE
irregular_chars-1.4.0.dist-info/METADATA
irregular_chars-1.4.0.dist-info/WHEEL
irregular_chars-1.4.0.dist-info/top_level.txt
irregular_chars-1.4.0.dist-info/RECORD
